catdagger/ModColor.py
catdagger/__init__.py
catdagger/__main__.py
catdagger/filters.py
catdagger/fits_tools.py
catdagger/gauss2.py
catdagger/geometry.py
catdagger/logger.py
catdagger/lsm_tools.py
catdagger/tiled_tesselator.py
catdagger-0.2.1.data/scripts/dagger
catdagger-0.2.1.dist-info/METADATA
catdagger-0.2.1.dist-info/WHEEL
catdagger-0.2.1.dist-info/top_level.txt
catdagger-0.2.1.dist-info/RECORD
