Metadata-Version: 2.1
Name: catdagger
Version: 0.2.1
Summary: An automatic differential gain catalog tagger
Home-page: https://github.com/bennahugo/catdagger
Author: Benjamin Hugo
Author-email: bhugo@ska.ac.za
License: GNU GPL v3
Platform: UNKNOWN
Classifier: Development Status :: 3 - Alpha
Classifier: Intended Audience :: Science/Research
Classifier: License :: OSI Approved :: GNU General Public License v3 (GPLv3)
Classifier: Operating System :: POSIX :: Linux
Classifier: Programming Language :: Python
Classifier: Topic :: Scientific/Engineering :: Astronomy
Requires-Dist: numpy
Requires-Dist: astropy
Requires-Dist: scipy
Requires-Dist: astro-tigger-lsm
